{
  "name": "AUSGER composer repository",
  "homepage": "http://http://ausger.satis:8888/",
  "repositories": [
    {
      "type": "vcs",
      "url": "https://github.com/ausger/myporto.git"
    },
    {
      "type": "vcs",
      "url": "https://github.com/ausger/onestepcheckout-v340.git"
    },
    {
      "type": "vcs",
      "url": "https://github.com/ausger/Dhl_Intraship.git"
    },
    {
      "type": "vcs",
      "url": "https://github.com/riconeitzel/German_LocalePack_de_DE.git"
    },
    {
      "type": "vcs",
      "url": "https://github.com/ausger/disable-compare.git"
    },
    {
      "type": "vcs",
      "url": "https://github.com/AOEpeople/Aoe_Scheduler.git"

    },
    {
      "type": "vcs",
      "url": "https://github.com/aschroder/Magento-SMTP-Pro-Email-Extension.git"
    },
    {
      "type": "vcs",
      "url": "https://github.com/GordonLesti/Lesti_Fpc.git"
    },
    {
      "type": "vcs",
      "url": "https://github.com/steverobbins/Magento-Redismanager.git"
    },
    {
      "type": "vcs",
      "url": "https://github.com/colinmollenhour/Cm_Cache_Backend_Redis.git"
    },
    {
      "type": "vcs",
      "url": "https://github.com/ausger/magento-alipay.git"
    },
    {
      "type": "vcs",
      "url": "https://github.com/ausger/matrixshippingrate.git"
    },
    {
      "type": "vcs",
      "url": "https://github.com/integer-net/Autoshipping.git"
    },
    {
      "type": "vcs",
      "url": "https://github.com/firegento/firegento-pdf.git"
    },
    {
      "type": "vcs",
      "url": "https://github.com/magento-hackathon/FireGento_FlexCms.git"
    },
    {
      "type": "vcs",
      "url": "https://github.com/magento-hackathon/Hackathon_PromoCodeMessages.git"
    },
    {
      "type": "vcs",
      "url": "https://github.com/magento-hackathon/AsyncIndex.git"
    },
    {
      "type": "vcs",
      "url": "https://github.com/magento-hackathon/E-MailPreview.git"
    },
    {
      "type": "vcs",
      "url": "https://github.com/magento-hackathon/MageTrashApp.git"
    },
    {
      "type": "vcs",
      "url": "https://github.com/ausger/juicy_geoip.git"
    },
    {
      "type": "vcs",
      "url": "https://github.com/magento-hackathon/EAVCleaner.git"
    },
    {
      "type": "vcs",
      "url": "https://github.com/magento-hackathon/HoneySpam.git"
    },
    {
      "type": "vcs",
      "url": "https://github.com/aligent/Inchoo_MaxOrderAmount.git"
    },
    {
      "type": "vcs",
      "url": "https://github.com/AOEpeople/Aoe_Profiler.git"
    },
    {
      "type": "vcs",
      "url": "https://github.com/fbrnc/Aoe_JsCssTstamp.git"
    },
    {
      "type": "vcs",
      "url": "https://github.com/fbrnc/Aoe_QuoteCleaner.git"
    },
    {
      "type": "vcs",
      "url": "https://github.com/ausger/speedsteradvanced.git"
    },
    {
      "type": "vcs",
      "url": "https://github.com/nexcess/magento-turpentine.git"
    },
    {
      "type": "vcs",
      "url": "https://github.com/ausger/Aschroder_SetStartOrderNumber-0.3.git"
    },
    {
      "type": "vcs",
      "url": "https://github.com/AOEpeople/Aoe_TemplateHints.git"
    },
    {
      "type": "vcs",
      "url": "https://github.com/ausger/EUCookieLawBanner.git"
    },
    {
      "type": "vcs",
      "url": "https://github.com/astorm/LayoutViewer.git"
    },
    {
      "type": "vcs",
      "url": "https://github.com/ausger/SphinxSearch.git"
    }
  ],
  "require-all": true
}